Metadata-Version: 2.1
Name: power-attention-cuda
Version: 0.1.0
Summary: CUDA implementation of power attention
Requires-Python: >=3.11
Requires-Dist: torch>=2.6.0
Requires-Dist: numpy>=2.2
